decisiontree_lite/__init__.py
decisiontree_lite/decisiontree.py
decisiontree_lite/utils.py
decisiontree_lite-0.0.2.dist-info/LICENSE
decisiontree_lite-0.0.2.dist-info/METADATA
decisiontree_lite-0.0.2.dist-info/WHEEL
decisiontree_lite-0.0.2.dist-info/top_level.txt
decisiontree_lite-0.0.2.dist-info/RECORD
