Metadata-Version: 2.1
Name: decisiontree-lite
Version: 0.0.2
Summary: A custom implementation of decision tree classifier.
Home-page: https://github.com/Harisiva-rg/decisiontree_lite
Author: Harisiva R G
Author-email: harisivarg@gmail.com
License: MIT
Platform: UNKNOWN
Classifier: License :: OSI Approved :: MIT License
Classifier: Programming Language :: Python :: 3.10
Classifier: Operating System :: OS Independent
Requires-Python: >=3.10
License-File: LICENSE
Requires-Dist: numpy
Requires-Dist: scikit-learn
Requires-Dist: pandas
